beachbot_config/__init__.py
beachbot_config/config.py
beachbot_config/py.typed
beachbot_config-0.0.2.dist-info/METADATA
beachbot_config-0.0.2.dist-info/WHEEL
beachbot_config-0.0.2.dist-info/licenses/LICENSE
beachbot_config-0.0.2.dist-info/RECORD
